.coveragerc
.travis.yml
AUTHORS
CHANGES.rst
ChangeLog
LICENSE.txt
README.rst
TODO.txt
requirements.txt
setup.cfg
setup.py
spread
test-requirements.txt
doc/Makefile
doc/api.rst
doc/changelog.rst
doc/commands.rst
doc/conf.py
doc/configuring.rst
doc/extending.rst
doc/faq.rst
doc/index.rst
doc/installation.rst
doc/make.bat
doc/plugins.rst
doc/requirements.txt
doc/tutorial.rst
doc/_static/icon.png
doc/_static/logo.png
doc/_static/monk.png
doc/_static/wizard1.png
doc/_static/wizard2.png
doc/_static/wizard3.png
doc/_static/wizard4.png
doc/_static/wizard5.png
doc/_static/src/icon.xcf
doc/_static/src/logo.xcf
doc/_themes/LICENSE
doc/_themes/README
doc/_themes/flask_theme_support.py
doc/_themes/flask/layout.html
doc/_themes/flask/relations.html
doc/_themes/flask/theme.conf
doc/_themes/flask/static/flasky.css_t
doc/_themes/flask/static/small_flask.css
spreads/__init__.py
spreads/cli.py
spreads/config_default.yaml
spreads/plugin.py
spreads/util.py
spreads/workflow.py
spreads.egg-info/PKG-INFO
spreads.egg-info/SOURCES.txt
spreads.egg-info/dependency_links.txt
spreads.egg-info/entry_points.txt
spreads.egg-info/not-zip-safe
spreads.egg-info/requires.txt
spreads.egg-info/top_level.txt
spreads/vendor/__init__.py
spreads/vendor/confit.py
spreads/vendor/pathlib.py
spreadsplug/__init__.py
spreadsplug/autorotate.py
spreadsplug/colorcorrect.py
spreadsplug/djvubind.py
spreadsplug/pdfbeads.py
spreadsplug/scantailor.py
spreadsplug/tesseract.py
spreadsplug/dev/__init__.py
spreadsplug/dev/chdkcamera.py
spreadsplug/gui/__init__.py
spreadsplug/gui/gui.py
spreadsplug/gui/gui.qrc
spreadsplug/gui/gui_rc.py
spreadsplug/gui/pixmaps/monk.png
tests/.coverage
tests/__init__.py
tests/autorotate_test.py
tests/chdkcamera_test.py
tests/cli_test.py
tests/gui_test.py
tests/plugin_test.py
tests/scantailor_test.py
tests/workflow_test.py