Metadata-Version: 1.1
Name: spreads
Version: v0.4.2
Summary: Book digitization workflow suite
Home-page: http://github.com/jbaiter/spreads
Author: Johannes Baiter
Author-email: johannes.baiter@gmail.com
License: MIT
Keywords: digitization
Platform: UNKNOWN
Classifier: Development Status :: 4 - Beta
Classifier: Environment :: Console
Classifier: Environment :: X11 Applications :: Qt
Classifier: Intended Audience :: End Users/Desktop
Classifier: Intended Audience :: Education
Classifier: Intended Audience :: Science/Research
Classifier: License :: OSI Approved :: MIT License
Classifier: Operating System :: POSIX
Classifier: Programming Language :: Python :: 2.7
Classifier: Topic :: Multimedia :: Graphics :: Capture
Classifier: Topic :: Multimedia :: Graphics :: Graphics Conversion
